versjon/__init__.py
versjon/__main__.py
versjon/template_render.py
versjon/versjon_tool.py
versjon/templates/footer.html
versjon/templates/head.html
versjon/templates/header.html
versjon/templates/index.html
versjon/templates/stable_index.html
versjon-2.3.0.dist-info/METADATA
versjon-2.3.0.dist-info/WHEEL
versjon-2.3.0.dist-info/entry_points.txt
versjon-2.3.0.dist-info/top_level.txt
versjon-2.3.0.dist-info/RECORD
