Metadata-Version: 2.1
Name: versjon
Version: 2.3.0
Summary: Tool for generating a json file with the name and url of versions.
Home-page: https://github.com/steinwurf/
Author: Steinwurf ApS
Author-email: contact@steinwurf.com
License: BSD 3-clause "New" or "Revised" License
Keywords: versjon
Platform: UNKNOWN
Classifier: Development Status :: 5 - Production/Stable
Classifier: Intended Audience :: Developers
Classifier: License :: OSI Approved :: BSD License
Classifier: Operating System :: OS Independent
Classifier: Programming Language :: Python :: 2.7
Classifier: Programming Language :: Python :: 3.4
Classifier: Programming Language :: Python :: 3.5
Classifier: Programming Language :: Python :: 3.6
Classifier: Programming Language :: Python
Classifier: Topic :: Documentation
Classifier: Topic :: Software Development :: Documentation
Classifier: Topic :: Utilities
Requires-Dist: beautifulsoup4
Requires-Dist: click
Requires-Dist: colorama
Requires-Dist: semantic-version
Requires-Dist: sphobjinv
